pyreco/__init__.py
pyreco/cross_validation.py
pyreco/custom_models.py
pyreco/datasets.py
pyreco/graph_analyzer.py
pyreco/initializer.py
pyreco/layers.py
pyreco/metrics.py
pyreco/models.py
pyreco/network_prop_extractor.py
pyreco/node_analyzer.py
pyreco/node_selector.py
pyreco/optimizers.py
pyreco/plotting.py
pyreco/pruning.py
pyreco/remove_transients.py
pyreco/utils_data.py
pyreco/utils_networks.py
pyreco-1.1.0.dist-info/METADATA
pyreco-1.1.0.dist-info/WHEEL
pyreco-1.1.0.dist-info/licenses/AUTHORS.rst
pyreco-1.1.0.dist-info/licenses/LICENSE.txt
pyreco-1.1.0.dist-info/RECORD
