Metadata-Version: 2.4
Name: pyreco
Version: 1.1.0
Summary: A Python Reservoir Computing Library for Time Series Forecasting and Research created by CPSME TU Berlin.
Project-URL: Homepage, https://github.com/Cyber-Physical-Systems-in-Mech-Eng/pyReCo
Project-URL: Issues, https://github.com/Cyber-Physical-Systems-in-Mech-Eng/pyReCo/issues
Author-email: Merten Stender <merten.stender@tu-berlin.de>, Manish Yadav <manish.yadav@tu-berlin.de>
License-File: AUTHORS.rst
License-File: LICENSE.txt
Classifier: License :: OSI Approved :: Apache Software License
Classifier: Operating System :: OS Independent
Classifier: Programming Language :: Python :: 3
Requires-Python: >=3.7
Requires-Dist: matplotlib>=3.5.0
Requires-Dist: networkx>=2.5
Requires-Dist: numpy>=1.21.0
Requires-Dist: scikit-learn>=1.0.0
